cryptouri/__init__.py
cryptouri-0.0.0.dist-info/METADATA
cryptouri-0.0.0.dist-info/RECORD
cryptouri-0.0.0.dist-info/WHEEL
cryptouri-0.0.0.dist-info/top_level.txt
